kotormcp/__init__.py
kotormcp/server.py
kotormcp-0.1.1.dist-info/METADATA
kotormcp-0.1.1.dist-info/WHEEL
kotormcp-0.1.1.dist-info/entry_points.txt
kotormcp-0.1.1.dist-info/top_level.txt
kotormcp-0.1.1.dist-info/RECORD
