Metadata-Version: 2.4
Name: kotormcp
Version: 0.1.1
Summary: Model Context Protocol server exposing Knights of the Old Republic resources for AI agents.
Author: th3w1zard1
Maintainer-email: th3w1zard1 <halomastar@gmail.com>
License: LGPL-3.0-or-later
Project-URL: Homepage, https://github.com/th3w1zard1/KotorMCP
Project-URL: Documentation, https://github.com/OldRepublicDevs/PyKotor/wiki
Project-URL: Repository, https://github.com/th3w1zard1/KotorMCP.git
Project-URL: Issues, https://github.com/th3w1zard1/KotorMCP/issues
Project-URL: Changelog, https://github.com/th3w1zard1/KotorMCP/releases
Keywords: kotor,kotor1,kotor2,tsl,mcp,model-context-protocol,ai,llm,agent,modding,game-resources
Classifier: Development Status :: 4 - Beta
Classifier: Intended Audience :: Developers
Classifier: License :: OSI Approved :: GNU Lesser General Public License v3 or later (LGPLv3+)
Classifier: Operating System :: OS Independent
Classifier: Programming Language :: Python :: 3
Classifier: Programming Language :: Python :: 3.11
Classifier: Programming Language :: Python :: 3.12
Classifier: Topic :: Games/Entertainment
Classifier: Topic :: Software Development :: Libraries :: Python Modules
Classifier: Topic :: Software Development :: Build Tools
Classifier: Environment :: Console
Classifier: Typing :: Typed
Requires-Python: >=3.11
Requires-Dist: mcp>=0.1.1
Requires-Dist: pykotor>=2.0.2
Requires-Dist: uvicorn[standard]>=0.30.0
Provides-Extra: dev
Requires-Dist: pytest>=7.0.0; extra == "dev"
Requires-Dist: pytest-cov>=4.0.0; extra == "dev"
Requires-Dist: ruff>=0.1.0; extra == "dev"
Requires-Dist: mypy>=1.0.0; extra == "dev"
